thenmap/thenmap.py
thenmap-1.0.0.dist-info/DESCRIPTION.rst
thenmap-1.0.0.dist-info/LICENSE.txt
thenmap-1.0.0.dist-info/METADATA
thenmap-1.0.0.dist-info/RECORD
thenmap-1.0.0.dist-info/WHEEL
thenmap-1.0.0.dist-info/metadata.json
thenmap-1.0.0.dist-info/pbr.json
thenmap-1.0.0.dist-info/top_level.txt
