Metadata-Version: 2.0
Name: thenmap
Version: 1.0.0
Summary: A Thenmap API wrapper
Home-page: https://github.com/jplusplus/thenmap-python
Author: Leonard Wallentin, J++ Stockholm
Author-email: stockholm@jplusplus.org
License: MIT
Platform: UNKNOWN
Requires-Dist: requests
Requires-Dist: shapely
Requires-Dist: six
